hytools_lite/__init__.py
hytools_lite/base.py
hytools_lite/io/__init__.py
hytools_lite/io/envi.py
hytools_lite/io/neon.py
hy_tools_lite-1.1.1.dist-info/LICENSE
hy_tools_lite-1.1.1.dist-info/METADATA
hy_tools_lite-1.1.1.dist-info/WHEEL
hy_tools_lite-1.1.1.dist-info/top_level.txt
hy_tools_lite-1.1.1.dist-info/RECORD
